{
	"Add to bookmarks": "بک مارکس میں شامل کریں",
	"All browsing data has been deleted.": "تمام براؤزنگ کے اعداد و شمار کو خارج کر دیا گیا ہے.",
	"Always Show Bookmarks Bar": "ہمیشہ مارک بار ظاہر",
	"Bookmark has been added.": "بک مارک شامل کر دیا گیا ہے۔",
	"Bookmark has been deleted.": "بک مارک حذف کردیا گیا ہے۔",
	"Bookmarks": "بک مارک",
	"CLEAR BROWSING DATA": "واضح براؤزنگ کے اعداد و شمار",
	"Continue where I left off": "میں چھوڑ دیا جہاں آگے",
	"DESELECT ALL": "تمام غیرمنتخب کریں",
	"Delete": "حذف کریں",
	"Delete from bookmarks": "بک مارکس سے حذف کریں",
	"Do you want to clear all browsing data?": "کیا آپ تمام براؤزنگ ڈیٹا صاف کرنا چاہتے ہیں؟",
	"Do you want to delete all bookmarks?": "کیا آپ تمام بک مارکس حذف کرنا چاہتے ہیں؟",
	"Do you want to delete all history?": "کیا آپ تمام سرگزشت حذف کرنا چاہتے ہیں؟",
	"Do you want to delete the selected bookmark(s)?": "کیا آپ منتخبہ بک مارک(س) حذف کرنا چاہتے ہیں؟",
	"Do you want to delete the selected history?": "کیا آپ منتخبہ سرگزشت حذف کرنا چاہتے ہیں؟",
	"Enter URL": "URL درج کریں",
	"Exit Full Screen": "پوری سکرین خروج کریں",
	"Exit app": "ایپ سے باہر نکلیں",
	"Full screen": "فل اسکرین",
	"History": "تاریخ",
	"Home page:": "مرکزی صفحہ:",
	"Menu": "مینو",
	"Most Visited Sites": "سب سے زیادہ کا دورہ کیا سائٹس",
	"NO": "نہیں",
	"Next": "اگلا",
	"OK": "ٹھیک ہے",
	"Off": "آف",
	"On": "پر",
	"On Startup": "سٹارٹاپ پر",
	"Open the New Tab page": "نیا ٹیب صفحہ کھولیں",
	"Previous": "گزشتہ",
	"RECENTLY CLOSED": "حال ہی میں بند کر دیا",
	"Refresh": "ریفریش کریں",
	"SELECT ALL": "تمام منتخب کریں",
	"Search": "تلاش کریں",
	"Search Engines": "تلاش کے انجن",
	"Selected bookmark(s) have been deleted.": "منتخبہ بک مارکس(س) حذف کردی گئی ہے۔",
	"Selected history has been deleted.": "منتخبہ سرگزشت حذف کردی گئی ہے۔",
	"Settings": "ترتیبات",
	"There is no bookmark.": "کوئی بُک مارک نہیں ہے۔",
	"There is no history.": "کوئی ہسٹری نہیں ہے۔",
	"This webpage is not available": "اس ویب صفحہ دستیاب نہیں ہے",
	"YES": "جی ہاں",
	"Zoom": "زوم کریں"
}
